{
  "main": {
    "id": "bd77f7bbf619e307",
    "type": "split",
    "children": [
      {
        "id": "64e20ccd51edd96d",
        "type": "tabs",
        "children": [
          {
            "id": "0389745b8ecbeeac",
            "type": "leaf",
            "state": {
              "type": "empty",
              "state": {},
              "icon": "lucide-file",
              "title": "New tab"
            }
          }
        ],
        "stacked": true
      }
    ],
    "direction": "vertical"
  },
  "left": {
    "id": "fbf5d82b3ce56cbc",
    "type": "split",
    "children": [
      {
        "id": "d792b1a70017cfc2",
        "type": "tabs",
        "children": [
          {
            "id": "8d18eccd8c856ee2",
            "type": "leaf",
            "state": {
              "type": "file-explorer",
              "state": {
                "sortOrder": "alphabetical",
                "autoReveal": false
              },
              "icon": "lucide-folder-closed",
              "title": "Files"
            }
          },
          {
            "id": "5dae7eaa69e8f0f8",
            "type": "leaf",
            "state": {
              "type": "search",
              "state": {
                "query": "",
                "matchingCase": false,
                "explainSearch": false,
                "collapseAll": false,
                "extraContext": false,
                "sortOrder": "alphabetical"
              },
              "icon": "lucide-search",
              "title": "Search"
            }
          },
          {
            "id": "0551ff11fba6ae2e",
            "type": "leaf",
            "state": {
              "type": "bookmarks",
              "state": {},
              "icon": "lucide-bookmark",
              "title": "Bookmarks"
            }
          },
          {
            "id": "5c5387345b77a06e",
            "type": "leaf",
            "state": {
              "type": "notebook-navigator",
              "state": {},
              "icon": "notebook-navigator",
              "title": "Notebook Navigator"
            }
          }
        ],
        "currentTab": 3
      }
    ],
    "direction": "horizontal",
    "width": 339.5
  },
  "right": {
    "id": "ac53ac83f79e3541",
    "type": "split",
    "children": [
      {
        "id": "ffeee6218ce1bf07",
        "type": "tabs",
        "dimension": 50.294117647058826,
        "children": [
          {
            "id": "e8248ad7f3c5ce90",
            "type": "leaf",
            "state": {
              "type": "calendar",
              "state": {},
              "icon": "lucide-ghost",
              "title": "calendar"
            }
          },
          {
            "id": "e1d9b37cab136f4d",
            "type": "leaf",
            "state": {
              "type": "tag",
              "state": {
                "sortOrder": "frequency",
                "useHierarchy": true,
                "showSearch": false,
                "searchQuery": ""
              },
              "icon": "lucide-tags",
              "title": "Tags"
            }
          },
          {
            "id": "dfc4f6244fce1a51",
            "type": "leaf",
            "state": {
              "type": "all-properties",
              "state": {
                "sortOrder": "frequency",
                "showSearch": false,
                "searchQuery": ""
              },
              "icon": "lucide-archive",
              "title": "All properties"
            }
          },
          {
            "id": "62c33df3cc0c93e4",
            "type": "leaf",
            "state": {
              "type": "outline",
              "state": {
                "file": "00 Terminal/Untitled.md",
                "followCursor": false,
                "showSearch": false,
                "searchQuery": ""
              },
              "icon": "lucide-list",
              "title": "Outline of Untitled"
            }
          }
        ],
        "currentTab": 3
      },
      {
        "id": "366a1994cdfcd4ba",
        "type": "tabs",
        "dimension": 49.705882352941174,
        "children": [
          {
            "id": "b0dae7252840b26e",
            "type": "leaf",
            "state": {
              "type": "file-properties",
              "state": {
                "file": "30 Journal/2026-01-19.md"
              },
              "icon": "lucide-info",
              "title": "File properties for 2026-01-19"
            }
          },
          {
            "id": "1163b9eca1cb44c3",
            "type": "leaf",
            "state": {
              "type": "backlink",
              "state": {
                "file": "30 Journal/2026-01-16.md",
                "collapseAll": false,
                "extraContext": false,
                "sortOrder": "alphabetical",
                "showSearch": false,
                "searchQuery": "",
                "backlinkCollapsed": false,
                "unlinkedCollapsed": true
              },
              "icon": "links-coming-in",
              "title": "Backlinks for 2026-01-16"
            }
          },
          {
            "id": "fca03524a0d9587a",
            "type": "leaf",
            "state": {
              "type": "outgoing-link",
              "state": {
                "file": "10 Projects/Act Once Creative/actonecreative.md",
                "linksCollapsed": false,
                "unlinkedCollapsed": true
              },
              "icon": "links-going-out",
              "title": "Outgoing links from actonecreative"
            }
          },
          {
            "id": "daeab53ce3b23fad",
            "type": "leaf",
            "state": {
              "type": "git-view",
              "state": {},
              "icon": "git-pull-request",
              "title": "Source Control"
            }
          }
        ],
        "currentTab": 3
      }
    ],
    "direction": "horizontal",
    "width": 200,
    "collapsed": true
  },
  "left-ribbon": {
    "hiddenItems": {
      "switcher:Open quick switcher": false,
      "graph:Open graph view": false,
      "canvas:Create new canvas": false,
      "daily-notes:Open today's daily note": false,
      "templates:Insert template": false,
      "command-palette:Open command palette": false,
      "bases:Create new base": false,
      "obsidian-book-search-plugin:Create new book note": false,
      "templater-obsidian:Templater": false,
      "omnisearch:Omnisearch": false,
      "callout-manager:Insert Callout": false,
      "obsidian-git:Open Git source control": false,
      "notebook-navigator:Notebook Navigator": false
    }
  },
  "active": "5c5387345b77a06e",
  "lastOpenFiles": [
    "conflict-files-obsidian-git.md",
    "00 Terminal/Untitled.md",
    "30 Journal/2026-02-24.md",
    "10 Projects/Act One Creative/Blog/Cold Outreach in 2026.md",
    "10 Projects/Act One Creative/Act One Creative.md",
    "10 Projects/Act One Creative/Blog/What 5 Years of Freelance Video Editing Taught Me.md",
    "30 Journal/2026-01-26.md",
    "10 Projects/Projects.md",
    "00 Terminal/What 5 Years of Freelance Video Editing Taught Me.md",
    "10 Projects/Act One Creative/Blog/What 5 Years of Freelance Video Editing Taught Me.html",
    "20 Hobbies/Reading/Books/Buyology - Martin Lindstrom.md",
    "30 Journal/2026-01-25.md",
    "10 Projects/Act One Creative/Blog/How A Comprehensive Marketing Plan Helped Raise Money for Some Furry Friends - Case Study.md",
    "30 Journal/2026-01-23.md",
    "30 Journal/2026-01-22.md",
    "30 Journal/2026-01-21.md",
    "98 Archive/Tasks Archive.md",
    "10 Projects/Act One Creative/Todo.md",
    "98 Archive",
    "30 Journal/2026-01-19.md",
    "10 Projects/Act One Creative/Blog/Buyology - Truth and Lies About Why We Buy.md",
    "20 Hobbies/Reading/Library.md",
    "99 Templates/blogpost.md",
    "10 Projects/Blog/Untitled.md",
    "10 Projects/Blog",
    "10 Projects/BlogUntitled.md",
    "Meetings/Untitled.md",
    "Meetings",
    "10 Projects/Act Once Creative/Blog/test.md",
    "30 Journal/2026-01-18.md",
    "00 Terminal/blogposts.base",
    "10 Projects/Act One Creative/Blog",
    "10 Projects/Act One Creative",
    "10 Projects/Act One Creative/Blogs",
    "10 Projects/Act One Creative",
    "20 Hobbies/Reading/Book Notes",
    "97 Attachments/Empire of the Vampire - Jay Kristoff.jpg",
    "97 Attachments/Pasted image 20260115153315.png",
    "97 Attachments/The Name of the Wind Cover.png",
    "97 Attachments/The Name of the Wind - Patrick Rothfuss.jpg",
    "97 Attachments/urban_architecture.jpg"
  ]
}